pdftranscript/__init__.py
pdftranscript/config.py
pdftranscript/dictionary.json
pdftranscript/pdf2html.py
pdftranscript/test.py
pdftranscript/transcript.py
pdftranscript/ttf.py
pdftranscript-1.0.3.dist-info/METADATA
pdftranscript-1.0.3.dist-info/WHEEL
pdftranscript-1.0.3.dist-info/entry_points.txt
pdftranscript-1.0.3.dist-info/licenses/LICENSE.txt
pdftranscript-1.0.3.dist-info/RECORD
