Metadata-Version: 2.3
Name: pdftranscript
Version: 1.0.3
Summary: PDF to semantic HTML conversion.
Author-email: František Malina <fmalina@pm.me>
Keywords: HTML,PDF,conversion
Classifier: Intended Audience :: Developers
Classifier: Programming Language :: Python :: 3
Classifier: Topic :: Software Development :: Libraries
Classifier: Topic :: Utilities
Requires-Python: >=3.9
Requires-Dist: cssselect
Requires-Dist: freetype-py
Requires-Dist: lxml
Requires-Dist: python-dotenv
